interact/__init__.py
interact/__main__.py
interact/base.py
interact/error.py
interact/fields.py
interact/settings.py
interact/utils.py
interact/when.py
interact_cli-0.5.0.dist-info/LICENSE
interact_cli-0.5.0.dist-info/METADATA
interact_cli-0.5.0.dist-info/WHEEL
interact_cli-0.5.0.dist-info/top_level.txt
interact_cli-0.5.0.dist-info/RECORD
