Metadata-Version: 2.1
Name: interact-cli
Version: 0.5.0
Summary: Interactive command line tool.
Home-page: https://github.com/caizhengxin/interact-cli
Author: jankincai
Author-email: jankincai12@gmail.com
Maintainer: jankincai
Maintainer-email: jankincai12@gmail.com
License: BSD
Download-URL: https://github.com/caizhengxin/interact-cli.git
Project-URL: Documentation, https://interact-cli.readthedocs.io
Project-URL: Source Code, https://github.com/caizhengxin/interact-cli
Keywords: interact-cli,interact,cli
Platform: any
Classifier: Development Status :: 4 - Beta
Classifier: Environment :: Console
Classifier: Operating System :: OS Independent
Classifier: Intended Audience :: Developers
Classifier: License :: OSI Approved :: BSD License
Classifier: Programming Language :: Python
Classifier: Programming Language :: Python :: 3
Classifier: Programming Language :: Python :: 3.6
Classifier: Programming Language :: Python :: 3.7
Classifier: Programming Language :: Python :: 3 :: Only
Classifier: Topic :: Software Development :: Libraries :: Python Modules
